odoo10_addon_mrp_bom_component_menu-10.0.1.0.0-py2.7-nspkg.pth
odoo/addons/mrp_bom_component_menu/README.rst
odoo/addons/mrp_bom_component_menu/__init__.py
odoo/addons/mrp_bom_component_menu/__manifest__.py
odoo/addons/mrp_bom_component_menu/static/description/icon.png
odoo/addons/mrp_bom_component_menu/views/mrp_bom_component_view.xml
odoo10_addon_mrp_bom_component_menu-10.0.1.0.0.dist-info/DESCRIPTION.rst
odoo10_addon_mrp_bom_component_menu-10.0.1.0.0.dist-info/METADATA
odoo10_addon_mrp_bom_component_menu-10.0.1.0.0.dist-info/RECORD
odoo10_addon_mrp_bom_component_menu-10.0.1.0.0.dist-info/WHEEL
odoo10_addon_mrp_bom_component_menu-10.0.1.0.0.dist-info/metadata.json
odoo10_addon_mrp_bom_component_menu-10.0.1.0.0.dist-info/namespace_packages.txt
odoo10_addon_mrp_bom_component_menu-10.0.1.0.0.dist-info/top_level.txt
